m_librarian/__init__.py
m_librarian/__version__.py
m_librarian/compat.py
m_librarian/config.py
m_librarian/db.py
m_librarian/download.py
m_librarian/glst.py
m_librarian/inp.py
m_librarian/pbar.py
m_librarian/search.py
m_librarian/translations.py
m_librarian/glst/License.txt
m_librarian/glst/README.rus.txt
m_librarian/glst/genres_fb2_flibusta.glst
m_librarian/glst/genres_fb2_librusec.glst
m_librarian/glst/genres_nonfb2.glst
m_librarian/translations_dir/ru.mo
m_librarian/translations_dir/ru.po
m_librarian/web/__init__.py
m_librarian/web/app.py
m_librarian/web/server.py
m_librarian/web/utils.py
m_librarian/web/static/style.css
m_librarian/web/views/__init__.py
m_librarian/web/views/download.py
m_librarian/web/views/download.tmpl
m_librarian/web/views/index.py
m_librarian/web/views/index.tmpl
m_librarian/web/views/layout.py
m_librarian/web/views/layout.tmpl
m_librarian/web/views/list_authors.py
m_librarian/web/views/list_authors.tmpl
m_librarian/web/views/list_books.py
m_librarian/web/views/list_books.tmpl
m_librarian/web/views/search_authors.py
m_librarian/web/views/search_authors.tmpl
m_librarian/web/views/search_authors_form.py
m_librarian/web/views/search_authors_form.tmpl
m_librarian/web/views/search_books.py
m_librarian/web/views/search_books.tmpl
m_librarian/web/views/search_books_form.py
m_librarian/web/views/search_books_form.tmpl
m_librarian-0.4.2.data/scripts/ml-import.py
m_librarian-0.4.2.data/scripts/ml-initdb.py
m_librarian-0.4.2.data/scripts/ml-search.py
m_librarian-0.4.2.data/scripts/ml-web.py
m_librarian-0.4.2.dist-info/METADATA
m_librarian-0.4.2.dist-info/RECORD
m_librarian-0.4.2.dist-info/WHEEL
m_librarian-0.4.2.dist-info/top_level.txt
